{
  "Core": {
    "AssetsRootDirectoryPath": "Assets",
    "CustomGameLoopSteps": [ "SceneLoadingSystem" ],
    "FixedUpdatesPerFrameLimit": 30,
    "FixedUpdatesPerSecond": 60,
    "ShowAllEntitiesCount": false,
    "ShowRootEntitiesCount": false,
    "ShowFps": false,
    "ShowFrameTime": false,
    "ShowGameLoopStatistics": false,
    "ShowTotalFrames": false,
    "ShowTotalTime": false,
    "StartUpSceneBehavior": "Main"
  },
  "Physics": {
    "RenderCollisionGeometry": false
  },
  "Rendering": {
    "EnableVSync": false,
    "ScreenHeight": 720,
    "ScreenWidth": 1280,
    "SortingLayersOrder": [
      "Background",
      "Ground",
      "CrateSpot",
      "TileObject",
      "UI",
      "VFX"
    ]
  }
}